fin_art/__init__.py
fin_art/art_generator.py
fin_art-7.0.dist-info/METADATA
fin_art-7.0.dist-info/WHEEL
fin_art-7.0.dist-info/top_level.txt
fin_art-7.0.dist-info/RECORD
